{"卡路里":
	{"lyrics": [
    	{"start":"", "end":"" , "text": ""},
	{"start":"", "end":"" , "text": "每天起床第一句 先给自己打个气"},
	{"start":"", "end":"" , "text": "每次多吃一粒米 都要说声对不起"},
	{"start":"", "end":"" , "text": "魔镜魔镜看看我 我的锁骨在哪里"},
	{"start":"", "end":"" , "text": ""},
	{"start":"", "end":"" , "text": "美丽 我要美丽 我要变成万人迷"},
	{"start":"", "end":"" , "text": "Pose pose"},
	{"start":"", "end":"" , "text": ""},
	{"start":"", "end":"" , "text": "我要变成万人迷"},
	{"start":"", "end":"" , "text": ""},
	{"start":"", "end":"" , "text": "Pose pose"},
	{"start":"", "end":"" , "text": "为了变成小蛮腰 天天提着一口气"},
	{"start":"", "end":"" , "text": "为了穿上比基尼 吃草吃成沙拉精"},
	{"start":"", "end":"" , "text": "天生丽质难自弃 可惜吃啥我都不腻"},
	{"start":"", "end":"" , "text": "努力 我要努力 我要变成万人迷"},
	{"start":"", "end":"" , "text": ""},
	{"start":"", "end":"" , "text": "Wow"},
	{"start":"", "end":"" , "text": "卡路里卡路里卡路"},
	{"start":"", "end":"" , "text": ""},
	{"start":"", "end":"" , "text": "卡路里卡路里卡路"},
	{"start":"", "end":"" , "text": ""},
	{"start":"", "end":"" , "text": "卡路里卡路里卡路"},
	{"start":"", "end":"" , "text": ""},
	{"start":"", "end":"" , "text": "卡路里卡路里卡路"},
	{"start":"", "end":"" , "text": ""},
	{"start":"", "end":"" , "text": "卡路里我的天敌"},
	{"start":"", "end":"" , "text": ""},
	{"start":"", "end":"" , "text": "燃烧我的卡路里"},
	{"start":"", "end":"" , "text": ""},
	{"start":"", "end":"" , "text": "拜拜 甜甜圈 珍珠奶茶方便面"},
	{"start":"", "end":"" , "text": ""},
	{"start":"", "end":"" , "text": "火锅米饭大盘鸡"},
	{"start":"", "end":"" , "text": ""},
	{"start":"", "end":"" , "text": "拿走拿走别客气"},
	{"start":"", "end":"" , "text": ""},
	{"start":"", "end":"" , "text": ""},
	{"start":"", "end":"" , "text": ""},
	{"start":"", "end":"" , "text": "拜拜 咖啡因 戒掉可乐戒油腻"},
	{"start":"", "end":"" , "text": ""},
	{"start":"", "end":"" , "text": "沙发外卖玩游戏"},
	{"start":"", "end":"" , "text": ""},
	{"start":"", "end":"" , "text": ""},
	{"start":"", "end":"" , "text": ""},
	{"start":"", "end":"" , "text": "别再熬夜伤身体"},
	{"start":"", "end":"" , "text": ""},
	{"start":"", "end":"" , "text": ""},
	{"start":"", "end":"" , "text": ""},
	{"start":"", "end":"" , "text": "来来 后转体 高温瑜伽仰卧起"},
	{"start":"", "end":"" , "text": ""},
	{"start":"", "end":"" , "text": "动感单车普拉提"},
	{"start":"", "end":"" , "text": ""},
	{"start":"", "end":"" , "text": ""},
	{"start":"", "end":"" , "text": ""},
	{"start":"", "end":"" , "text": "保温杯里泡枸杞"},
	{"start":"", "end":"" , "text": ""},
	{"start":"", "end":"" , "text": ""},
	{"start":"", "end":"" , "text": ""},
	{"start":"", "end":"" , "text": "来来 深呼吸 晨跑夜跑游几米"},
	{"start":"", "end":"" , "text": ""},
	{"start":"", "end":"" , "text": "平板哑铃划船机 不达目的不放弃"},
	{"start":"", "end":"" , "text": ""},
	{"start":"", "end":"" , "text": ""},
	{"start":"", "end":"" , "text": ""},
	{"start":"", "end":"" , "text": "为了变成小蛮腰 天天提着一口气"},
	{"start":"", "end":"" , "text": ""},
	{"start":"", "end":"" , "text": ""},
	{"start":"", "end":"" , "text": ""},
	{"start":"", "end":"" , "text": "为了穿上比基尼 吃草吃成沙拉精"},
	{"start":"", "end":"" , "text": ""},
	{"start":"", "end":"" , "text": ""},
	{"start":"", "end":"" , "text": ""},
	{"start":"", "end":"" , "text": "天生丽质难自弃 可惜吃啥我都不腻"},
	{"start":"", "end":"" , "text": ""},
	{"start":"", "end":"" , "text": "努力 我要努力 我要变成万人迷"},
	{"start":"", "end":"" , "text": ""},
	{"start":"", "end":"" , "text": "Wow"},
	{"start":"", "end":"" , "text": ""},
	{"start":"", "end":"" , "text": "卡路里卡路里卡路"},
	{"start":"", "end":"" , "text": ""},
	{"start":"", "end":"" , "text": "卡路里卡路里卡路"},
	{"start":"", "end":"" , "text": ""},
	{"start":"", "end":"" , "text": "卡路里卡路里卡路"},
	{"start":"", "end":"" , "text": ""},
	{"start":"", "end":"" , "text": "卡路里卡路里卡路"},
	{"start":"", "end":"" , "text": ""},
	{"start":"", "end":"" , "text": "卡路里我的天敌"},
	{"start":"", "end":"" , "text": ""},
	{"start":"", "end":"" , "text": "燃烧我的卡路里"},
	{"start":"", "end":"" , "text": ""},
	{"start":"", "end":"" , "text": "拜拜 甜甜圈 珍珠奶茶方便面"},
	{"start":"", "end":"" , "text": ""},
	{"start":"", "end":"" , "text": "火锅米饭大盘鸡 拿走拿走别客气"},
	{"start":"", "end":"" , "text": ""},
	{"start":"", "end":"" , "text": "拜拜 咖啡因 戒掉可乐戒油腻"},
	{"start":"", "end":"" , "text": ""},
	{"start":"", "end":"" , "text": "沙发外卖玩游戏 别再熬夜伤身体"},
	{"start":"", "end":"" , "text": ""},
	{"start":"", "end":"" , "text": "来来 后转体 高温瑜伽仰卧起"},
	{"start":"", "end":"" , "text": ""},
	{"start":"", "end":"" , "text": "动感单车普拉提 保温杯里泡枸杞"},
	{"start":"", "end":"" , "text": ""},
	{"start":"", "end":"" , "text": "来来 深呼吸 晨跑夜跑游几米"},
	{"start":"", "end":"" , "text": ""},
	{"start":"", "end":"" , "text": "平板哑铃划船机 不达目的不放弃"},
	{"start":"", "end":"" , "text": ""},
	{"start":"", "end":"" , "text": "奇了怪了 小的时候明明是 妈妈说"},
	{"start":"", "end":"" , "text": ""},
	{"start":"", "end":"" , "text": "吃光盘中餐粒粒 皆辛苦"},
	{"start":"", "end":"" , "text": ""},
	{"start":"", "end":"" , "text": "直到最爱的裙子的扣子都系不上了"},
	{"start":"", "end":"" , "text": ""},
	{"start":"", "end":"" , "text": "原来吃得掉 甩不掉 更辛苦"},
	{"start":"", "end":"" , "text": ""},
	{"start":"", "end":"" , "text": "希望 体重 秤是坏的"},
	{"start":"", "end":"" , "text": ""},
	{"start":"", "end":"" , "text": "帅哥 爱唐代的"},
	{"start":"", "end":"" , "text": ""},
	{"start":"", "end":"" , "text": "不如跟着节奏没在怕的 努努力"},
	{"start":"", "end":"" , "text": ""},
	{"start":"", "end":"" , "text": "别让卡路里卡路里 卡住你"},
	{"start":"", "end":"" , "text": ""},
	{"start":"", "end":"" , "text": "不达目的不放弃"},
	{"start":"", "end":"" , "text": ""},
	{"start":"", "end":"" , "text": "燃烧我的卡路里"},
	{"start":"", "end":"" , "text": ""},
	{"start":"", "end":"" , "text": "拜拜 甜甜圈 珍珠奶茶方便面"},
	{"start":"", "end":"" , "text": ""},
	{"start":"", "end":"" , "text": "火锅米饭大盘鸡 拿走拿走别客气"},
	{"start":"", "end":"" , "text": ""},
	{"start":"", "end":"" , "text": "拜拜 咖啡因 戒掉可乐戒油腻"},
	{"start":"", "end":"" , "text": ""},
	{"start":"", "end":"" , "text": "沙发外卖玩游戏 别再熬夜伤身体"},
	{"start":"", "end":"" , "text": ""},
	{"start":"", "end":"" , "text": "来来 后转体 高温瑜伽仰卧起"},
	{"start":"", "end":"" , "text": ""},
	{"start":"", "end":"" , "text": "动感单车普拉提 保温杯里泡枸杞"},
	{"start":"", "end":"" , "text": ""},
	{"start":"", "end":"" , "text": "来来 深呼吸 晨跑夜跑游几米"},
	{"start":"", "end":"" , "text": ""},
	{"start":"", "end":"" , "text": "平板哑铃划船机 不达目的不放弃"},
	{"start":"", "end":"" , "text": ""},
	{"start":"", "end":"" , "text": "不放弃"},
	{"start":"", "end":"" , "text": ""},
	{"start":"", "end":"" , "text": "燃烧我的卡路里"},
	{"start":"", "end":"" , "text": ""},
	{"start":"", "end":"" , "text": "不放弃"},
	{"start":"", "end":"" , "text": ""},
	{"start":"", "end":"" , "text": "燃烧我的卡路里"},
	{"start":"", "end":"" , "text": ""},
	{"start":"", "end":"" , "text": "我要变成万人迷"},
]}}